dataset/__init__.py
dataset/chunked.py
dataset/database.py
dataset/table.py
dataset/types.py
dataset/util.py
dataset-1.6.2.dist-info/LICENSE.txt
dataset-1.6.2.dist-info/METADATA
dataset-1.6.2.dist-info/WHEEL
dataset-1.6.2.dist-info/namespace_packages.txt
dataset-1.6.2.dist-info/top_level.txt
dataset-1.6.2.dist-info/RECORD
