Metadata-Version: 2.1
Name: dataset
Version: 1.6.2
Summary: Toolkit for Python-based database access.
Home-page: http://github.com/pudo/dataset
Author: Friedrich Lindenberg, Gregor Aisch, Stefan Wehrmeyer
Author-email: friedrich.lindenberg@gmail.com
License: MIT
Keywords: sql sqlalchemy etl loading utility
Classifier: Development Status :: 3 - Alpha
Classifier: Intended Audience :: Developers
Classifier: License :: OSI Approved :: MIT License
Classifier: Operating System :: OS Independent
Classifier: Programming Language :: Python :: 3.5
Classifier: Programming Language :: Python :: 3.6
Classifier: Programming Language :: Python :: 3.7
Classifier: Programming Language :: Python :: 3.8
Classifier: Programming Language :: Python :: 3.9
Provides-Extra: dev
License-File: LICENSE.txt
